{
 "hash": "0x4149EC12B780F09BBDEE2C18755742B620D392DD8385D1487ACCFE6D3B6903B7",
 "statements": [
  {
   "kind": "Variable",
   "data": {
    "mutable": false,
    "name": "my_print",
    "hash": "0xEB759C75BAE1C8B6",
    "annotation": { "id": 0 },
    "value": {
     "kind": "Import",
     "data": {
      "expression": {
       "kind": "Literal",
       "data": {
        "native": "str",
        "value": "./examples/extern/function1/my_print.ac",
        "id": 1,
        "resolvedType": { "kind": "Primitive", "data": { "native": "str", "params": [] } }
       },
       "id": 2,
       "resolvedType": {
        "kind": "Primitive",
        "data": { "native": "str", "params": {/* circular */} }
       }
      },
      "id": 3,
      "resolvedModule": {
       "hash": "0x46BBAA0B2EFBBD17316A322326E286E259BFA40D89E50EBAE2F742358DD16372",
       "statements": [
        {
         "kind": "Typedef",
         "data": {
          "name": "MyObject",
          "type": {
           "kind": "Object",
           "data": {
            "fields": [
             {
              "mutable": false,
              "name": "a",
              "hash": "0xCA978112CA1BBDCA",
              "type": {
               "kind": "Primitive",
               "data": { "native": "i32", "params": [], "id": 1 },
               "id": 2
              }
             },
             {
              "mutable": false,
              "name": "b",
              "hash": "0x3E23E8160039594A",
              "type": {
               "kind": "Primitive",
               "data": { "native": "i32", "params": [], "id": 4 },
               "id": 5
              }
             }
            ],
            "id": 7
           },
           "id": 8
          },
          "template": { "params": [], "id": 0 },
          "id": 9
         },
         "id": 10
        },
        { "kind": "Empty", "data": { "id": 11 }, "id": 12 },
        {
         "kind": "Variable",
         "data": {
          "mutable": false,
          "name": "my_print",
          "hash": "0xEB759C75BAE1C8B6",
          "annotation": { "id": 13 },
          "value": {
           "kind": "Function",
           "data": {
            "template": { "params": [], "id": 14 },
            "params": [
             {
              "name": "a",
              "annotation": {
               "type": {
                "kind": "Primitive",
                "data": { "native": "i32", "params": [], "id": 15 },
                "id": 16
               },
               "id": 17
              },
              "resolvedType": {
               "kind": "Primitive",
               "data": { "native": "i32", "params": {/* circular */}, "id": 15 },
               "id": 16
              }
             },
             {
              "name": "b",
              "annotation": {
               "type": {
                "kind": "Primitive",
                "data": { "native": "i32", "params": [], "id": 18 },
                "id": 19
               },
               "id": 20
              },
              "resolvedType": {
               "kind": "Primitive",
               "data": { "native": "i32", "params": {/* circular */}, "id": 18 },
               "id": 19
              }
             }
            ],
            "ret": {
             "type": {
              "kind": "Identifier",
              "data": {
               "name": "MyObject",
               "params": [],
               "id": 21,
               "resolvedShorthand": {
                "kind": "Typedef",
                "data": {
                 "name": "MyObject",
                 "type": { "kind": "Object", "data": {/* circular */}, "id": 8 },
                 "template": { "params": {/* circular */}, "id": 0 },
                 "id": 9
                }
               }
              },
              "id": 22
             },
             "id": 23
            },
            "block": {
             "statements": [
              {
               "kind": "Unsafe",
               "data": {
                "content": "\n    printf(\"Hello, A:%d\n\", __a->data.i32);\n    printf(\"Hello, B:%d\n\", __b->data.i32);\n  ",
                "id": 24
               },
               "id": 25
              },
              {
               "kind": "Return",
               "data": {
                "expression": {
                 "kind": "Object",
                 "data": {
                  "fields": [
                   {
                    "mutable": false,
                    "name": "a",
                    "hash": "0xCA978112CA1BBDCA",
                    "expression": {
                     "kind": "Binary",
                     "data": {
                      "operator": "Substraction",
                      "expression1": {
                       "kind": "Binary",
                       "data": {
                        "operator": "Addition",
                        "expression1": {
                         "kind": "Identifier",
                         "data": {
                          "name": "a",
                          "id": 26,
                          "resolvedReference": {
                           "kind": "Closure",
                           "data": {
                            "idx": 0,
                            "name": "a",
                            "resolvedReference": {
                             "kind": "Param",
                             "data": {
                              "name": "a",
                              "annotation": { "type": {/* circular */}, "id": 17 },
                              "resolvedType": { "kind": "Primitive", "data": {/* circular */}, "id": 16 }
                             }
                            },
                            "resolvedType": {
                             "kind": "Primitive",
                             "data": { "native": "i32", "params": {/* circular */}, "id": 15 },
                             "id": 16
                            }
                           }
                          },
                          "resolvedType": {
                           "kind": "Primitive",
                           "data": { "native": "i32", "params": {/* circular */}, "id": 15 },
                           "id": 16
                          }
                         },
                         "resolvedType": {
                          "kind": "Primitive",
                          "data": { "native": "i32", "params": {/* circular */}, "id": 15 },
                          "id": 16
                         }
                        },
                        "expression2": {
                         "kind": "Literal",
                         "data": {
                          "native": "i32",
                          "value": "10",
                          "id": 27,
                          "resolvedType": { "kind": "Primitive", "data": { "native": "i32", "params": [] } }
                         },
                         "resolvedType": {
                          "kind": "Primitive",
                          "data": { "native": "i32", "params": {/* circular */} }
                         }
                        },
                        "resolvedPrioritization": true,
                        "resolvedType": {
                         "kind": "Primitive",
                         "data": { "native": "i32", "params": {/* circular */} }
                        }
                       },
                       "resolvedType": {
                        "kind": "Primitive",
                        "data": { "native": "i32", "params": {/* circular */} }
                       }
                      },
                      "expression2": {
                       "kind": "Identifier",
                       "data": {
                        "name": "b",
                        "id": 28,
                        "resolvedReference": {
                         "kind": "Closure",
                         "data": {
                          "idx": 1,
                          "name": "b",
                          "resolvedReference": {
                           "kind": "Param",
                           "data": {
                            "name": "b",
                            "annotation": { "type": {/* circular */}, "id": 20 },
                            "resolvedType": { "kind": "Primitive", "data": {/* circular */}, "id": 19 }
                           }
                          },
                          "resolvedType": {
                           "kind": "Primitive",
                           "data": { "native": "i32", "params": {/* circular */}, "id": 18 },
                           "id": 19
                          }
                         }
                        },
                        "resolvedType": {
                         "kind": "Primitive",
                         "data": { "native": "i32", "params": {/* circular */}, "id": 18 },
                         "id": 19
                        }
                       },
                       "id": 29,
                       "resolvedType": {
                        "kind": "Primitive",
                        "data": { "native": "i32", "params": {/* circular */}, "id": 18 },
                        "id": 19
                       }
                      },
                      "id": 32,
                      "resolvedType": {
                       "kind": "Primitive",
                       "data": { "native": "i32", "params": {/* circular */}, "id": 18 },
                       "id": 19
                      }
                     },
                     "id": 33,
                     "resolvedType": {
                      "kind": "Primitive",
                      "data": { "native": "i32", "params": {/* circular */}, "id": 18 },
                      "id": 19
                     }
                    }
                   },
                   {
                    "mutable": false,
                    "name": "b",
                    "hash": "0x3E23E8160039594A",
                    "expression": {
                     "kind": "Binary",
                     "data": {
                      "operator": "Addition",
                      "expression1": {
                       "kind": "Unary",
                       "data": {
                        "operator": "Negative",
                        "expression": {
                         "kind": "Identifier",
                         "data": {
                          "name": "b",
                          "id": 34,
                          "resolvedReference": {
                           "kind": "Closure",
                           "data": {
                            "idx": 1,
                            "name": "b",
                            "resolvedReference": {/* circular */},
                            "resolvedType": {/* circular */}
                           }
                          },
                          "resolvedType": {
                           "kind": "Primitive",
                           "data": { "native": "i32", "params": {/* circular */}, "id": 18 },
                           "id": 19
                          }
                         },
                         "id": 35,
                         "resolvedType": {
                          "kind": "Primitive",
                          "data": { "native": "i32", "params": {/* circular */}, "id": 18 },
                          "id": 19
                         }
                        },
                        "id": 36,
                        "resolvedType": {
                         "kind": "Primitive",
                         "data": { "native": "i32", "params": {/* circular */}, "id": 18 },
                         "id": 19
                        }
                       },
                       "resolvedType": {
                        "kind": "Primitive",
                        "data": { "native": "i32", "params": {/* circular */}, "id": 18 },
                        "id": 19
                       }
                      },
                      "expression2": {
                       "kind": "Literal",
                       "data": {
                        "native": "i32",
                        "value": "10",
                        "id": 37,
                        "resolvedType": { "kind": "Primitive", "data": { "native": "i32", "params": [] } }
                       },
                       "id": 38,
                       "resolvedType": {
                        "kind": "Primitive",
                        "data": { "native": "i32", "params": {/* circular */} }
                       }
                      },
                      "id": 39,
                      "resolvedType": {
                       "kind": "Primitive",
                       "data": { "native": "i32", "params": {/* circular */} }
                      }
                     },
                     "id": 40,
                     "resolvedType": {
                      "kind": "Primitive",
                      "data": { "native": "i32", "params": {/* circular */} }
                     }
                    }
                   }
                  ],
                  "id": 41,
                  "resolvedClosures": [
                   {
                    "idx": 0,
                    "name": "a",
                    "resolvedReference": { "kind": "Param", "data": {/* circular */} },
                    "resolvedType": { "kind": "Primitive", "data": {/* circular */}, "id": 16 }
                   },
                   {
                    "idx": 1,
                    "name": "b",
                    "resolvedReference": { "kind": "Param", "data": {/* circular */} },
                    "resolvedType": { "kind": "Primitive", "data": {/* circular */}, "id": 19 }
                   }
                  ],
                  "resolvedType": {
                   "kind": "Object",
                   "data": {
                    "fields": [
                     {
                      "mutable": false,
                      "name": "a",
                      "hash": "0xCA978112CA1BBDCA",
                      "type": {
                       "kind": "Primitive",
                       "data": { "native": "i32", "params": {/* circular */}, "id": 18 },
                       "id": 19
                      }
                     },
                     {
                      "mutable": false,
                      "name": "b",
                      "hash": "0x3E23E8160039594A",
                      "type": {
                       "kind": "Primitive",
                       "data": { "native": "i32", "params": {/* circular */} }
                      }
                     }
                    ]
                   }
                  }
                 },
                 "id": 42,
                 "resolvedType": { "kind": "Object", "data": { "fields": {/* circular */} } }
                },
                "id": 43
               },
               "id": 44
              }
             ],
             "id": 45
            },
            "id": 46,
            "resolvedClosures": [],
            "resolvedReturns": [
             {
              "expression": {
               "kind": "Object",
               "data": {/* circular */},
               "id": 42,
               "resolvedType": {/* circular */}
              },
              "id": 43
             }
            ],
            "resolvedType": {
             "kind": "Function",
             "data": {
              "params": [
               {
                "name": "a",
                "type": {
                 "kind": "Primitive",
                 "data": { "native": "i32", "params": {/* circular */}, "id": 15 },
                 "id": 16
                }
               },
               {
                "name": "b",
                "type": {
                 "kind": "Primitive",
                 "data": { "native": "i32", "params": {/* circular */}, "id": 18 },
                 "id": 19
                }
               }
              ],
              "ret": {
               "kind": "Identifier",
               "data": {
                "name": "MyObject",
                "params": {/* circular */},
                "id": 21,
                "resolvedShorthand": {/* circular */}
               },
               "id": 22
              }
             }
            }
           },
           "id": 47,
           "resolvedType": {
            "kind": "Function",
            "data": { "params": {/* circular */}, "ret": {/* circular */} }
           }
          },
          "id": 48,
          "resolvedType": {
           "kind": "Function",
           "data": { "params": {/* circular */}, "ret": {/* circular */} }
          }
         },
         "id": 49
        },
        {
         "kind": "Return",
         "data": {
          "expression": {
           "kind": "Object",
           "data": {
            "fields": [
             {
              "mutable": false,
              "name": "my_print",
              "hash": "0xEB759C75BAE1C8B6",
              "expression": {
               "kind": "Identifier",
               "data": {
                "name": "my_print",
                "id": 50,
                "resolvedReference": {
                 "kind": "Closure",
                 "data": {
                  "idx": 0,
                  "name": "my_print",
                  "resolvedReference": {
                   "kind": "Variable",
                   "data": {
                    "mutable": false,
                    "name": "my_print",
                    "hash": "0xEB759C75BAE1C8B6",
                    "annotation": { "id": 13 },
                    "value": {
                     "kind": "Function",
                     "data": {/* circular */},
                     "id": 47,
                     "resolvedType": {/* circular */}
                    },
                    "id": 48,
                    "resolvedType": { "kind": "Function", "data": {/* circular */} }
                   }
                  },
                  "resolvedType": {
                   "kind": "Function",
                   "data": { "params": {/* circular */}, "ret": {/* circular */} }
                  }
                 }
                },
                "resolvedType": {
                 "kind": "Function",
                 "data": { "params": {/* circular */}, "ret": {/* circular */} }
                }
               },
               "id": 51,
               "resolvedType": {
                "kind": "Function",
                "data": { "params": {/* circular */}, "ret": {/* circular */} }
               }
              }
             }
            ],
            "id": 52,
            "resolvedClosures": [
             {
              "idx": 0,
              "name": "my_print",
              "resolvedReference": { "kind": "Variable", "data": {/* circular */} },
              "resolvedType": { "kind": "Function", "data": {/* circular */} }
             }
            ],
            "resolvedType": {
             "kind": "Object",
             "data": {
              "fields": [
               {
                "mutable": false,
                "name": "my_print",
                "hash": "0xEB759C75BAE1C8B6",
                "type": {
                 "kind": "Function",
                 "data": { "params": {/* circular */}, "ret": {/* circular */} }
                }
               }
              ]
             }
            }
           },
           "id": 53,
           "resolvedType": { "kind": "Object", "data": { "fields": {/* circular */} } }
          },
          "id": 54
         },
         "id": 55
        }
       ]
      }
     },
     "id": 4,
     "resolvedType": undefined
    },
    "id": 5,
    "resolvedType": undefined
   },
   "id": 6
  },
  {
   "kind": "Variable",
   "data": {
    "mutable": false,
    "name": "res1",
    "hash": "0x0E405B9869CEFA2C",
    "annotation": { "id": 7 },
    "value": {
     "kind": "Call",
     "data": {
      "callee": {
       "kind": "Lookup",
       "data": {
        "expression": {
         "kind": "Identifier",
         "data": {
          "name": "my_print",
          "id": 8,
          "resolvedReference": {
           "kind": "Variable",
           "data": {
            "mutable": false,
            "name": "my_print",
            "hash": "0xEB759C75BAE1C8B6",
            "annotation": { "id": 0 },
            "value": {
             "kind": "Import",
             "data": {/* circular */},
             "id": 4,
             "resolvedType": undefined
            },
            "id": 5,
            "resolvedType": undefined
           }
          },
          "resolvedType": undefined
         },
         "resolvedType": undefined
        },
        "name": "my_print",
        "hash": "0xEB759C75BAE1C8B6",
        "id": 9
       },
       "resolvedType": undefined
      },
      "params": [
       {
        "kind": "Literal",
        "data": {
         "native": "i32",
         "value": "1",
         "id": 10,
         "resolvedType": { "kind": "Primitive", "data": { "native": "i32", "params": [] } }
        },
        "id": 11,
        "resolvedType": {
         "kind": "Primitive",
         "data": { "native": "i32", "params": {/* circular */} }
        }
       },
       {
        "kind": "Literal",
        "data": {
         "native": "i32",
         "value": "2",
         "id": 12,
         "resolvedType": { "kind": "Primitive", "data": { "native": "i32", "params": [] } }
        },
        "id": 13,
        "resolvedType": {
         "kind": "Primitive",
         "data": { "native": "i32", "params": {/* circular */} }
        }
       }
      ],
      "id": 14,
      "resolvedType": undefined
     },
     "id": 15,
     "resolvedType": undefined
    },
    "id": 16,
    "resolvedType": undefined
   },
   "id": 17
  },
  {
   "kind": "Expression",
   "data": {
    "expression": {
     "kind": "Call",
     "data": {
      "callee": {
       "kind": "Lookup",
       "data": {
        "expression": {
         "kind": "Identifier",
         "data": {
          "name": "my_print",
          "id": 18,
          "resolvedReference": {
           "kind": "Variable",
           "data": {
            "mutable": false,
            "name": "my_print",
            "hash": "0xEB759C75BAE1C8B6",
            "annotation": {/* circular */},
            "value": {/* circular */},
            "id": 5,
            "resolvedType": undefined
           }
          },
          "resolvedType": undefined
         },
         "resolvedType": undefined
        },
        "name": "my_print",
        "hash": "0xEB759C75BAE1C8B6",
        "id": 19
       },
       "resolvedType": undefined
      },
      "params": [
       {
        "kind": "Lookup",
        "data": {
         "expression": {
          "kind": "Identifier",
          "data": {
           "name": "res1",
           "id": 20,
           "resolvedReference": {
            "kind": "Variable",
            "data": {
             "mutable": false,
             "name": "res1",
             "hash": "0x0E405B9869CEFA2C",
             "annotation": { "id": 7 },
             "value": {
              "kind": "Call",
              "data": {/* circular */},
              "id": 15,
              "resolvedType": undefined
             },
             "id": 16,
             "resolvedType": undefined
            }
           },
           "resolvedType": undefined
          },
          "resolvedType": undefined
         },
         "name": "b",
         "hash": "0x3E23E8160039594A",
         "id": 21
        },
        "id": 22,
        "resolvedType": undefined
       },
       {
        "kind": "Lookup",
        "data": {
         "expression": {
          "kind": "Identifier",
          "data": {
           "name": "res1",
           "id": 23,
           "resolvedReference": {
            "kind": "Variable",
            "data": {
             "mutable": false,
             "name": "res1",
             "hash": "0x0E405B9869CEFA2C",
             "annotation": {/* circular */},
             "value": {/* circular */},
             "id": 16,
             "resolvedType": undefined
            }
           },
           "resolvedType": undefined
          },
          "resolvedType": undefined
         },
         "name": "a",
         "hash": "0xCA978112CA1BBDCA",
         "id": 24
        },
        "id": 25,
        "resolvedType": undefined
       }
      ],
      "id": 26,
      "resolvedType": undefined
     },
     "id": 27,
     "resolvedType": undefined
    },
    "id": 28
   },
   "id": 29
  },
  {
   "kind": "Variable",
   "data": {
    "mutable": false,
    "name": "res2",
    "hash": "0x1DB7EFD18753FBF0",
    "annotation": { "id": 30 },
    "value": {
     "kind": "Call",
     "data": {
      "callee": {
       "kind": "Lookup",
       "data": {
        "expression": {
         "kind": "Identifier",
         "data": {
          "name": "my_print",
          "id": 31,
          "resolvedReference": {
           "kind": "Variable",
           "data": {
            "mutable": false,
            "name": "my_print",
            "hash": "0xEB759C75BAE1C8B6",
            "annotation": {/* circular */},
            "value": {/* circular */},
            "id": 5,
            "resolvedType": undefined
           }
          },
          "resolvedType": undefined
         },
         "resolvedType": undefined
        },
        "name": "my_print",
        "hash": "0xEB759C75BAE1C8B6",
        "id": 32
       },
       "resolvedType": undefined
      },
      "params": [
       {
        "kind": "Literal",
        "data": {
         "native": "i32",
         "value": "3",
         "id": 33,
         "resolvedType": { "kind": "Primitive", "data": { "native": "i32", "params": [] } }
        },
        "id": 34,
        "resolvedType": {
         "kind": "Primitive",
         "data": { "native": "i32", "params": {/* circular */} }
        }
       },
       {
        "kind": "Literal",
        "data": {
         "native": "i32",
         "value": "4",
         "id": 35,
         "resolvedType": { "kind": "Primitive", "data": { "native": "i32", "params": [] } }
        },
        "id": 36,
        "resolvedType": {
         "kind": "Primitive",
         "data": { "native": "i32", "params": {/* circular */} }
        }
       }
      ],
      "id": 37,
      "resolvedType": undefined
     },
     "id": 38,
     "resolvedType": undefined
    },
    "id": 39,
    "resolvedType": undefined
   },
   "id": 40
  },
  {
   "kind": "Expression",
   "data": {
    "expression": {
     "kind": "Call",
     "data": {
      "callee": {
       "kind": "Lookup",
       "data": {
        "expression": {
         "kind": "Identifier",
         "data": {
          "name": "my_print",
          "id": 41,
          "resolvedReference": {
           "kind": "Variable",
           "data": {
            "mutable": false,
            "name": "my_print",
            "hash": "0xEB759C75BAE1C8B6",
            "annotation": {/* circular */},
            "value": {/* circular */},
            "id": 5,
            "resolvedType": undefined
           }
          },
          "resolvedType": undefined
         },
         "resolvedType": undefined
        },
        "name": "my_print",
        "hash": "0xEB759C75BAE1C8B6",
        "id": 42
       },
       "resolvedType": undefined
      },
      "params": [
       {
        "kind": "Lookup",
        "data": {
         "expression": {
          "kind": "Identifier",
          "data": {
           "name": "res2",
           "id": 43,
           "resolvedReference": {
            "kind": "Variable",
            "data": {
             "mutable": false,
             "name": "res2",
             "hash": "0x1DB7EFD18753FBF0",
             "annotation": { "id": 30 },
             "value": {
              "kind": "Call",
              "data": {/* circular */},
              "id": 38,
              "resolvedType": undefined
             },
             "id": 39,
             "resolvedType": undefined
            }
           },
           "resolvedType": undefined
          },
          "resolvedType": undefined
         },
         "name": "b",
         "hash": "0x3E23E8160039594A",
         "id": 44
        },
        "id": 45,
        "resolvedType": undefined
       },
       {
        "kind": "Lookup",
        "data": {
         "expression": {
          "kind": "Identifier",
          "data": {
           "name": "res2",
           "id": 46,
           "resolvedReference": {
            "kind": "Variable",
            "data": {
             "mutable": false,
             "name": "res2",
             "hash": "0x1DB7EFD18753FBF0",
             "annotation": {/* circular */},
             "value": {/* circular */},
             "id": 39,
             "resolvedType": undefined
            }
           },
           "resolvedType": undefined
          },
          "resolvedType": undefined
         },
         "name": "a",
         "hash": "0xCA978112CA1BBDCA",
         "id": 47
        },
        "id": 48,
        "resolvedType": undefined
       }
      ],
      "id": 49,
      "resolvedType": undefined
     },
     "id": 50,
     "resolvedType": undefined
    },
    "id": 51
   },
   "id": 52
  },
  {
   "kind": "Variable",
   "data": {
    "mutable": false,
    "name": "res3",
    "hash": "0x1D648848FD3C789C",
    "annotation": { "id": 53 },
    "value": {
     "kind": "Call",
     "data": {
      "callee": {
       "kind": "Lookup",
       "data": {
        "expression": {
         "kind": "Identifier",
         "data": {
          "name": "my_print",
          "id": 54,
          "resolvedReference": {
           "kind": "Variable",
           "data": {
            "mutable": false,
            "name": "my_print",
            "hash": "0xEB759C75BAE1C8B6",
            "annotation": {/* circular */},
            "value": {/* circular */},
            "id": 5,
            "resolvedType": undefined
           }
          },
          "resolvedType": undefined
         },
         "resolvedType": undefined
        },
        "name": "my_print",
        "hash": "0xEB759C75BAE1C8B6",
        "id": 55
       },
       "resolvedType": undefined
      },
      "params": [
       {
        "kind": "Literal",
        "data": {
         "native": "i32",
         "value": "5",
         "id": 56,
         "resolvedType": { "kind": "Primitive", "data": { "native": "i32", "params": [] } }
        },
        "id": 57,
        "resolvedType": {
         "kind": "Primitive",
         "data": { "native": "i32", "params": {/* circular */} }
        }
       },
       {
        "kind": "Literal",
        "data": {
         "native": "i32",
         "value": "6",
         "id": 58,
         "resolvedType": { "kind": "Primitive", "data": { "native": "i32", "params": [] } }
        },
        "id": 59,
        "resolvedType": {
         "kind": "Primitive",
         "data": { "native": "i32", "params": {/* circular */} }
        }
       }
      ],
      "id": 60,
      "resolvedType": undefined
     },
     "id": 61,
     "resolvedType": undefined
    },
    "id": 62,
    "resolvedType": undefined
   },
   "id": 63
  },
  {
   "kind": "Expression",
   "data": {
    "expression": {
     "kind": "Call",
     "data": {
      "callee": {
       "kind": "Lookup",
       "data": {
        "expression": {
         "kind": "Identifier",
         "data": {
          "name": "my_print",
          "id": 64,
          "resolvedReference": {
           "kind": "Variable",
           "data": {
            "mutable": false,
            "name": "my_print",
            "hash": "0xEB759C75BAE1C8B6",
            "annotation": {/* circular */},
            "value": {/* circular */},
            "id": 5,
            "resolvedType": undefined
           }
          },
          "resolvedType": undefined
         },
         "resolvedType": undefined
        },
        "name": "my_print",
        "hash": "0xEB759C75BAE1C8B6",
        "id": 65
       },
       "resolvedType": undefined
      },
      "params": [
       {
        "kind": "Lookup",
        "data": {
         "expression": {
          "kind": "Identifier",
          "data": {
           "name": "res3",
           "id": 66,
           "resolvedReference": {
            "kind": "Variable",
            "data": {
             "mutable": false,
             "name": "res3",
             "hash": "0x1D648848FD3C789C",
             "annotation": { "id": 53 },
             "value": {
              "kind": "Call",
              "data": {/* circular */},
              "id": 61,
              "resolvedType": undefined
             },
             "id": 62,
             "resolvedType": undefined
            }
           },
           "resolvedType": undefined
          },
          "resolvedType": undefined
         },
         "name": "b",
         "hash": "0x3E23E8160039594A",
         "id": 67
        },
        "id": 68,
        "resolvedType": undefined
       },
       {
        "kind": "Lookup",
        "data": {
         "expression": {
          "kind": "Identifier",
          "data": {
           "name": "res3",
           "id": 69,
           "resolvedReference": {
            "kind": "Variable",
            "data": {
             "mutable": false,
             "name": "res3",
             "hash": "0x1D648848FD3C789C",
             "annotation": {/* circular */},
             "value": {/* circular */},
             "id": 62,
             "resolvedType": undefined
            }
           },
           "resolvedType": undefined
          },
          "resolvedType": undefined
         },
         "name": "a",
         "hash": "0xCA978112CA1BBDCA",
         "id": 70
        },
        "id": 71,
        "resolvedType": undefined
       }
      ],
      "id": 72,
      "resolvedType": undefined
     },
     "id": 73,
     "resolvedType": undefined
    },
    "id": 74
   },
   "id": 75
  },
  {
   "kind": "Return",
   "data": {
    "expression": {
     "kind": "Object",
     "data": {
      "fields": [
       {
        "mutable": true,
        "name": "my_print",
        "hash": "0xEB759C75BAE1C8B6",
        "expression": {
         "kind": "Lookup",
         "data": {
          "expression": {
           "kind": "Identifier",
           "data": {
            "name": "my_print",
            "id": 76,
            "resolvedReference": {
             "kind": "Closure",
             "data": {
              "idx": 0,
              "name": "my_print",
              "resolvedReference": {
               "kind": "Variable",
               "data": {
                "mutable": false,
                "name": "my_print",
                "hash": "0xEB759C75BAE1C8B6",
                "annotation": {/* circular */},
                "value": {/* circular */},
                "id": 5,
                "resolvedType": undefined
               }
              },
              "resolvedType": undefined
             }
            },
            "resolvedType": undefined
           },
           "resolvedType": undefined
          },
          "name": "my_print",
          "hash": "0xEB759C75BAE1C8B6",
          "id": 77
         },
         "id": 78,
         "resolvedType": undefined
        }
       },
       {
        "mutable": false,
        "name": "change",
        "hash": "0x12EA12EACE7D655F",
        "expression": {
         "kind": "Function",
         "data": {
          "template": { "params": [], "id": 79 },
          "params": [],
          "ret": { "id": 80 },
          "block": {
           "statements": [
            {
             "kind": "Expression",
             "data": {
              "expression": {
               "kind": "Binary",
               "data": {
                "operator": "Assign",
                "expression1": {
                 "kind": "Identifier",
                 "data": {
                  "name": "res1",
                  "id": 81,
                  "resolvedReference": {
                   "kind": "Closure",
                   "data": {
                    "idx": 0,
                    "name": "res1",
                    "resolvedReference": {
                     "kind": "Closure",
                     "data": {
                      "idx": 1,
                      "name": "res1",
                      "resolvedReference": {
                       "kind": "Variable",
                       "data": {
                        "mutable": false,
                        "name": "res1",
                        "hash": "0x0E405B9869CEFA2C",
                        "annotation": {/* circular */},
                        "value": {/* circular */},
                        "id": 16,
                        "resolvedType": undefined
                       }
                      },
                      "resolvedType": undefined
                     }
                    },
                    "resolvedType": undefined
                   }
                  },
                  "resolvedType": undefined
                 },
                 "resolvedType": undefined
                },
                "expression2": {
                 "kind": "Identifier",
                 "data": {
                  "name": "res2",
                  "id": 82,
                  "resolvedReference": {
                   "kind": "Closure",
                   "data": {
                    "idx": 1,
                    "name": "res2",
                    "resolvedReference": {
                     "kind": "Closure",
                     "data": {
                      "idx": 2,
                      "name": "res2",
                      "resolvedReference": {
                       "kind": "Variable",
                       "data": {
                        "mutable": false,
                        "name": "res2",
                        "hash": "0x1DB7EFD18753FBF0",
                        "annotation": {/* circular */},
                        "value": {/* circular */},
                        "id": 39,
                        "resolvedType": undefined
                       }
                      },
                      "resolvedType": undefined
                     }
                    },
                    "resolvedType": undefined
                   }
                  },
                  "resolvedType": undefined
                 },
                 "id": 83,
                 "resolvedType": undefined
                },
                "id": 84,
                "resolvedType": undefined
               },
               "id": 85,
               "resolvedType": undefined
              },
              "id": 86
             },
             "id": 87
            }
           ],
           "id": 88
          },
          "id": 89,
          "resolvedClosures": [
           {
            "idx": 0,
            "name": "res1",
            "resolvedReference": { "kind": "Closure", "data": {/* circular */} },
            "resolvedType": undefined
           },
           {
            "idx": 1,
            "name": "res2",
            "resolvedReference": { "kind": "Closure", "data": {/* circular */} },
            "resolvedType": undefined
           }
          ],
          "resolvedReturns": [],
          "resolvedType": {
           "kind": "Function",
           "data": {
            "params": [],
            "ret": {
             "kind": "Primitive",
             "data": { "native": "unknown", "params": [] }
            }
           }
          }
         },
         "id": 90,
         "resolvedType": {
          "kind": "Function",
          "data": { "params": {/* circular */}, "ret": {/* circular */} }
         }
        }
       }
      ],
      "id": 91,
      "resolvedClosures": [
       {
        "idx": 0,
        "name": "my_print",
        "resolvedReference": { "kind": "Variable", "data": {/* circular */} },
        "resolvedType": undefined
       },
       {
        "idx": 1,
        "name": "res1",
        "resolvedReference": { "kind": "Variable", "data": {/* circular */} },
        "resolvedType": undefined
       },
       {
        "idx": 2,
        "name": "res2",
        "resolvedReference": { "kind": "Variable", "data": {/* circular */} },
        "resolvedType": undefined
       }
      ],
      "resolvedType": {
       "kind": "Object",
       "data": {
        "fields": [
         {
          "mutable": true,
          "name": "my_print",
          "hash": "0xEB759C75BAE1C8B6",
          "type": {
           "kind": "Primitive",
           "data": { "native": "unknown", "params": [] }
          }
         },
         {
          "mutable": false,
          "name": "change",
          "hash": "0x12EA12EACE7D655F",
          "type": {
           "kind": "Function",
           "data": { "params": {/* circular */}, "ret": {/* circular */} }
          }
         }
        ]
       }
      }
     },
     "id": 92,
     "resolvedType": { "kind": "Object", "data": { "fields": {/* circular */} } }
    },
    "id": 93
   },
   "id": 94
  }
 ]
}